quivr-0.8.1.dist-info/METADATA
quivr-0.8.1.dist-info/WHEEL
quivr-0.8.1.dist-info/entry_points.txt
quivr-0.8.1.dist-info/licenses/LICENSE
quivr/__init__.py
quivr/__version__.py
quivr/_arrow_utils.py
quivr/attributes.py
quivr/columns.py
quivr/concat.py
quivr/defragment.py
quivr/errors.py
quivr/linkage.py
quivr/py.typed
quivr/schemagraph.py
quivr/tables.py
quivr/validators.py
quivr-0.8.1.dist-info/RECORD
