Metadata-Version: 2.1
Name: quivr
Version: 0.8.1
Summary: Container library for working with tabular Arrow data
Author-Email: Spencer Nelson <spencer@spencerwnelson.com>
Project-URL: Source, https://github.com/B612-Asteroid-Institute/quivr
Requires-Python: >=3.9
Requires-Dist: pandas
Requires-Dist: pyarrow
Requires-Dist: numpy
Requires-Dist: mmh3
Requires-Dist: typing_extensions>=4.0.0
Provides-Extra: docs
Requires-Dist: sphinx==7.2.2; extra == "docs"
Requires-Dist: sphinx-autodoc-typehints; extra == "docs"
Requires-Dist: sphinx-copybutton; extra == "docs"
Requires-Dist: sphinx-toolbox; extra == "docs"
Requires-Dist: furo==2023.08.17; extra == "docs"
